kurv/__init__.py
kurv/compiler.py
kurv-1.2.dist-info/METADATA
kurv-1.2.dist-info/WHEEL
kurv-1.2.dist-info/top_level.txt
kurv-1.2.dist-info/RECORD
